dutch_pluralizer/__init__.py
dutch_pluralizer/__main__.py
dutch_pluralizer/mapping.py
dutch_pluralizer/pluralizer.py
dutch_pluralizer/pluralizer_cls.py
dutch_pluralizer/replacements.py
dutch_pluralizer/singularizer.py
dutch_pluralizer/speller.py
dutch_pluralizer/dict/LICENSE.md
dutch_pluralizer/dict/basiswoorden-gekeurd.txt
dutch_pluralizer/dict/nl-nl.aff
dutch_pluralizer/dict/nl-nl.dic
dutch_pluralizer/dict/nl-nl.txt
dutch_pluralizer/dict/nouns-meervouden.txt
dutch_pluralizer/strategies/__init__.py
dutch_pluralizer/strategies/helpers.py
dutch_pluralizer/strategies/pluralize_bastard_words.py
dutch_pluralizer/strategies/pluralize_by_hard_map.py
dutch_pluralizer/strategies/pluralize_by_latin.py
dutch_pluralizer/strategies/pluralize_eren.py
dutch_pluralizer/strategies/pluralize_long_vowel.py
dutch_pluralizer/strategies/pluralize_man.py
dutch_pluralizer/strategies/pluralize_oren.py
dutch_pluralizer/strategies/pluralize_with_en.py
dutch_pluralizer/strategies/pluralize_with_s.py
dutch_pluralizer-0.0.41.dist-info/LICENSE.md
dutch_pluralizer-0.0.41.dist-info/METADATA
dutch_pluralizer-0.0.41.dist-info/WHEEL
dutch_pluralizer-0.0.41.dist-info/entry_points.txt
dutch_pluralizer-0.0.41.dist-info/top_level.txt
dutch_pluralizer-0.0.41.dist-info/RECORD
