Metadata-Version: 2.1
Name: dutch-pluralizer
Version: 0.0.41
Summary: Generates Dutch plural and singular nouns in a very imperfect way using Hunspell dictionaries. Why imperfect? Because the Dutch language is full of exceptions.
Home-page: https://github.com/KeesCBakker/dutch-pluralizer-py
Author: Kees C. Bakker / KeesTalksTech
Author-email: info@keestalkstech.com
License: MIT
Platform: UNKNOWN
Classifier: License :: OSI Approved :: MIT License
Classifier: Programming Language :: Python :: 3.6
Classifier: Programming Language :: Python :: 3.7
Classifier: Programming Language :: Python :: 3.8
Requires-Dist: cython
Requires-Dist: cyhunspell
